charm_test-0.2.0.dist-info/DESCRIPTION.rst
charm_test-0.2.0.dist-info/METADATA
charm_test-0.2.0.dist-info/RECORD
charm_test-0.2.0.dist-info/WHEEL
charm_test-0.2.0.dist-info/metadata.json
charm_test-0.2.0.dist-info/pbr.json
charm_test-0.2.0.dist-info/top_level.txt
charmtest/__init__.py
charmtest/fixture.py
charmtest/paths.py
charmtest/testing.py
charmtest/juju/__init__.py
charmtest/juju/fixture.py
charmtest/juju/hooktools.py
charmtest/juju/tests/__init__.py
charmtest/juju/tests/test_fixture.py
charmtest/juju/tests/test_hooktools.py
charmtest/tests/__init__.py
charmtest/tests/test_fixture.py
charmtest/tests/test_testing.py
