Metadata-Version: 2.0
Name: charm-test
Version: 0.2.0
Summary: Helpers for unit-testing Juju charms
Home-page: https://github.com/freeekanayaka/charm-test
Author: Free Ekanayaka
Author-email: free.ekanayaka@gmail.com
License: MIT
Platform: POSIX
Classifier: License :: OSI Approved :: GNU Affero General Public License v3 or later (AGPLv3+)
Classifier: Operating System :: POSIX
Classifier: Programming Language :: Python :: 3
Requires-Dist: charmhelpers
Requires-Dist: fixtures
Requires-Dist: pbr
Requires-Dist: systemfixtures (>=0.6.0)
Requires-Dist: testtools
Provides-Extra: docs
Requires-Dist: sphinx; extra == 'docs'
Provides-Extra: test
Requires-Dist: coverage (>=4.2); extra == 'test'
